{
  "DisplayName": "_Name_",
  "Description": "_Description_",
  "CharacterGroup": 2,
  "TableID": "_NameId_",
  "StartingTokens": 3,
  "ForceAllAgentWeapons": false,
  "ForceDisableOutfitFunctionality": false,
  "UsesPurchasePriceIncrement": false,
  "HasPrimaryWeapon": true,
  "HasSecondaryWeapon": false,
  "HasTertiaryWeapon": true,
  "HasPrimaryItem": true,
  "HasSecondaryItem": true,
  "HasTertiaryItem": true,
  "HasShield": false,
  "ValidAmmoEras": [
    "Colonial",
    "WildWest",
    "TurnOfTheCentury",
    "WW1",
    "WW2",
    "PostWar",
    "Modern",
    "Futuristic",
    "Medieval"
  ],
  "ValidAmmoSets": [
    "Real"
  ],
  "GlobalAmmoBlacklist": [],
  "MagazineBlacklist": [],
  "RequireSightTable": {
    "Category": "Attachment",
    "Rarity": 1.0,
    "RequiredQuest": null,
    "ItemsToSpawn": 1,
    "MinAmmoCapacity": -1,
    "MaxAmmoCapacity": -1,
    "NumMagsSpawned": 3,
    "NumClipsSpawned": 3,
    "NumRoundsSpawned": 8,
    "SpawnMagAndClip": false,
    "BespokeAttachmentChance": 0.5,
    "IsCompatibleMagazine": false,
    "AutoPopulateGroup": true,
    "ForceSpawnAllSubPools": false,
    "IDOverride": [],
    "Eras": [],
    "Sets": [
      "Real"
    ],
    "Sizes": [],
    "Actions": [],
    "Modes": [],
    "ExcludedModes": [],
    "FeedOptions": [],
    "MountsAvailable": [],
    "RoundPowers": [],
    "Features": [
      "Reflex"
    ],
    "MeleeStyles": [],
    "MeleeHandedness": [],
    "MountTypes": [
      "Picatinny"
    ],
    "PowerupTypes": [],
    "ThrownTypes": [],
    "ThrownDamageTypes": [],
    "SubGroups": null
  },
  "PrimaryWeapon": {
    "PrimaryGroup":         
    {
      "Category": "Firearm",
      "Rarity": 1.0,
      "RequiredQuest": null,
      "ItemsToSpawn": 1,
      "MinAmmoCapacity": 1,
      "MaxAmmoCapacity": 99,
      "NumMagsSpawned": 0,
      "NumClipsSpawned": 0,
      "NumRoundsSpawned": 0,
      "SpawnMagAndClip": false,
      "BespokeAttachmentChance": 0.5,
      "IsCompatibleMagazine": false,
      "AutoPopulateGroup": false,
      "ForceSpawnAllSubPools": false,
      "IDOverride": [
        "_SignatureWeaponId_"
      ],
      "Eras": [],
      "Sets": [],
      "Sizes": [],
      "Actions": [],
      "Modes": [],
      "ExcludedModes": [],
      "FeedOptions": [],
      "MountsAvailable": [],
      "RoundPowers": [],
      "Features": [],
      "MeleeStyles": [],
      "MeleeHandedness": [],
      "MountTypes": [],
      "PowerupTypes": [],
      "ThrownTypes": [],
      "ThrownDamageTypes": [],
      "SubGroups": null
    },
    "BackupGroup": null
  },
  "SecondaryWeapon": {
    "PrimaryGroup": {
      "Category": "Powerup",
      "Rarity": 1.0,
      "RequiredQuest": null,
      "ItemsToSpawn": 1,
      "MinAmmoCapacity": 1,
      "MaxAmmoCapacity": 99,
      "NumMagsSpawned": 0,
      "NumClipsSpawned": 0,
      "NumRoundsSpawned": 0,
      "SpawnMagAndClip": false,
      "BespokeAttachmentChance": 0.5,
      "IsCompatibleMagazine": false,
      "AutoPopulateGroup": false,
      "ForceSpawnAllSubPools": false,
      "IDOverride": [],
      "Eras": [],
      "Sets": [],
      "Sizes": [],
      "Actions": [],
      "Modes": [],
      "ExcludedModes": [],
      "FeedOptions": [],
      "MountsAvailable": [],
      "RoundPowers": [],
      "Features": [],
      "MeleeStyles": [],
      "MeleeHandedness": [],
      "MountTypes": [],
      "PowerupTypes": [],
      "ThrownTypes": [],
      "ThrownDamageTypes": [],
      "SubGroups": null
    },
    "BackupGroup": null
  },
  "TertiaryWeapon": {
    "PrimaryGroup": {
      "Category": "MeleeWeapon",
      "Rarity": 1.0,
      "RequiredQuest": null,
      "ItemsToSpawn": 1,
      "MinAmmoCapacity": -1,
      "MaxAmmoCapacity": -1,
      "NumMagsSpawned": 0,
      "NumClipsSpawned": 0,
      "NumRoundsSpawned": 0,
      "SpawnMagAndClip": false,
      "BespokeAttachmentChance": 0.5,
      "IsCompatibleMagazine": false,
      "AutoPopulateGroup": false,
      "ForceSpawnAllSubPools": false,
      "IDOverride": ["_SignatureMeleeId_"],
      "Eras": [],
      "Sets": [],
      "Sizes": [],
      "Actions": [],
      "Modes": [],
      "ExcludedModes": [],
      "FeedOptions": [],
      "MountsAvailable": [],
      "RoundPowers": [],
      "Features": [],
      "MeleeStyles": [],
      "MeleeHandedness": [],
      "MountTypes": [],
      "PowerupTypes": [],
      "ThrownTypes": [],
      "ThrownDamageTypes": [],
      "SubGroups": null
    },
    "BackupGroup": null
  },
  "PrimaryItem": {
    "PrimaryGroup": {
      "Category": "Powerup",
      "Rarity": 1.0,
      "RequiredQuest": null,
      "ItemsToSpawn": 1,
      "MinAmmoCapacity": -1,
      "MaxAmmoCapacity": -1,
      "NumMagsSpawned": 0,
      "NumClipsSpawned": 0,
      "NumRoundsSpawned": 0,
      "SpawnMagAndClip": false,
      "BespokeAttachmentChance": 0.5,
      "IsCompatibleMagazine": false,
      "AutoPopulateGroup": false,
      "ForceSpawnAllSubPools": false,
      "IDOverride": [
        "Stielhandgranate",
        "CyberGrenade",
        "No69Grenade",
        "PinnedGrenadeF1M1916",
        "PinnedGrenadeF1Russia",
        "PinnedGrenadeFMK2",
        "PinnedGrenadeHE36MillsBomb",
        "PinnedGrenadeM219",
        "PinnedGrenadeM26",
        "PinnedGrenadeM340",
        "PinnedGrenadeM67",
        "PinnedGrenadeMk2",
        "PinnedGrenadeRG42",
        "PinnedGrenadeRG5",
        "PinnedGrenadeRGN",
        "PinnedGrenadeRGO",
        "PinnedGrenadeT13Beano",
        "PinnedGrenadeURG86",
        "PinnedGrenadeXM84"
      ],
      "Eras": [],
      "Sets": [],
      "Sizes": [],
      "Actions": [],
      "Modes": [],
      "ExcludedModes": [],
      "FeedOptions": [],
      "MountsAvailable": [],
      "RoundPowers": [],
      "Features": [],
      "MeleeStyles": [],
      "MeleeHandedness": [],
      "MountTypes": [],
      "PowerupTypes": [],
      "ThrownTypes": [],
      "ThrownDamageTypes": [],
      "SubGroups": null
    },
    "BackupGroup": null
  },
  "SecondaryItem": {
    "PrimaryGroup":{
    "Category": "Powerup",
    "Rarity": 1.0,
    "RequiredQuest": null,
    "ItemsToSpawn": "_StartingMagsAmount_",
    "MinAmmoCapacity": 1,
    "MaxAmmoCapacity": 99,
    "NumMagsSpawned": 0,
    "NumClipsSpawned": 0,
    "NumRoundsSpawned": 0,
    "SpawnMagAndClip": false,
    "BespokeAttachmentChance": 0.5,
    "IsCompatibleMagazine": false,
    "AutoPopulateGroup": false,
    "ForceSpawnAllSubPools": false,
    "IDOverride": "_MagazineIds_",
    "Eras": [],
    "Sets": [],
    "Sizes": [],
    "Actions": [],
    "Modes": [],
    "ExcludedModes": [],
    "FeedOptions": [],
    "MountsAvailable": [],
    "RoundPowers": [],
    "Features": [],
    "MeleeStyles": [],
    "MeleeHandedness": [],
    "MountTypes": [],
    "PowerupTypes": [],
    "ThrownTypes": [],
    "ThrownDamageTypes": [],
    "SubGroups": null
  },
    "BackupGroup": null
  },
  "TertiaryItem": {
    "PrimaryGroup": {
      "Category": "Attachment",
      "Rarity": 1.0,
      "RequiredQuest": null,
      "ItemsToSpawn": 1,
      "MinAmmoCapacity": -1,
      "MaxAmmoCapacity": -1,
      "NumMagsSpawned": 3,
      "NumClipsSpawned": 3,
      "NumRoundsSpawned": 8,
      "SpawnMagAndClip": false,
      "BespokeAttachmentChance": 0.5,
      "IsCompatibleMagazine": false,
      "AutoPopulateGroup": false,
      "ForceSpawnAllSubPools": true,
      "IDOverride": [],
      "Eras": [],
      "Sets": [],
      "Sizes": [],
      "Actions": [],
      "Modes": [],
      "ExcludedModes": [],
      "FeedOptions": [],
      "MountsAvailable": [],
      "RoundPowers": [],
      "Features": [],
      "MeleeStyles": [],
      "MeleeHandedness": [],
      "MountTypes": [],
      "PowerupTypes": [],
      "ThrownTypes": [],
      "ThrownDamageTypes": [],
      "SubGroups": [
        {
          "Category": "Attachment",
          "Rarity": 1.0,
          "RequiredQuest": null,
          "ItemsToSpawn": 1,
          "MinAmmoCapacity": -1,
          "MaxAmmoCapacity": -1,
          "NumMagsSpawned": 3,
          "NumClipsSpawned": 3,
          "NumRoundsSpawned": 8,
          "SpawnMagAndClip": false,
          "BespokeAttachmentChance": 0.5,
          "IsCompatibleMagazine": false,
          "AutoPopulateGroup": false,
          "ForceSpawnAllSubPools": false,
          "IDOverride": [
            "UtilityFlashlight"
          ],
          "Eras": [],
          "Sets": [],
          "Sizes": [],
          "Actions": [],
          "Modes": [],
          "ExcludedModes": [],
          "FeedOptions": [],
          "MountsAvailable": [],
          "RoundPowers": [],
          "Features": [],
          "MeleeStyles": [],
          "MeleeHandedness": [],
          "MountTypes": [],
          "PowerupTypes": [],
          "ThrownTypes": [],
          "ThrownDamageTypes": [],
          "SubGroups": null
        }
      ]
    },
    "BackupGroup": null
  },
  "Shield": {
    "PrimaryGroup": null,
    "BackupGroup": null
  },
  "EquipmentPools": [
    {
      "_Name": "cheap boolets H0",
      "Type": "Firearm",
      "IconName": "bullets.png",
      "TokenCost": 1,
      "TokenCostLimited": 1,
      "MinLevelAppears": 0,
      "MaxLevelAppears": 0,
      "SpawnsInSmallCase": false,
      "SpawnsInLargeCase": false,
      "PrimaryGroup": {
        "Category": "Cartridge",
        "Rarity": 10.0,
        "RequiredQuest": null,
        "ItemsToSpawn": "_10_AmmoShopMultiplier_",
        "MinAmmoCapacity": 6,
        "MaxAmmoCapacity": 13,
        "NumMagsSpawned": 3,
        "NumClipsSpawned": 3,
        "NumRoundsSpawned": 8,
        "SpawnMagAndClip": false,
        "BespokeAttachmentChance": 0.5,
        "IsCompatibleMagazine": false,
        "AutoPopulateGroup": false,
        "ForceSpawnAllSubPools": false,
        "IDOverride": [],
        "Eras": [],
        "Sets": [],
        "Sizes": [],
        "Actions": [],
        "Modes": [],
        "ExcludedModes": [],
        "FeedOptions": [],
        "MountsAvailable": [],
        "RoundPowers": [],
        "Features": [],
        "MeleeStyles": [],
        "MeleeHandedness": [],
        "MountTypes": [],
        "PowerupTypes": [],
        "ThrownTypes": [],
        "ThrownDamageTypes": [],
        "SubGroups": [
          {
            "Category": "Firearm",
            "Rarity": 10.0,
            "RequiredQuest": null,
            "ItemsToSpawn": "_10_AmmoShopMultiplier_",
            "MinAmmoCapacity": 6,
            "MaxAmmoCapacity": 13,
            "NumMagsSpawned": 3,
            "NumClipsSpawned": 3,
            "NumRoundsSpawned": 8,
            "SpawnMagAndClip": false,
            "BespokeAttachmentChance": 0.5,
            "IsCompatibleMagazine": false,
            "AutoPopulateGroup": false,
            "ForceSpawnAllSubPools": false,
            "IDOverride": [
              "_AmmoIdTiers0_"
            ],
            "Eras": [],
            "Sets": [],
            "Sizes": [],
            "Actions": [],
            "Modes": [],
            "ExcludedModes": [],
            "FeedOptions": [],
            "MountsAvailable": [],
            "RoundPowers": [],
            "Features": [],
            "MeleeStyles": [],
            "MeleeHandedness": [],
            "MountTypes": [],
            "PowerupTypes": [],
            "ThrownTypes": [],
            "ThrownDamageTypes": [],
            "SubGroups": null
          }
        ]
      },
      "BackupGroup": null
    },
    {
      "_Name": "cheap boolets H1",
      "Type": "Firearm",
      "IconName": "bullets.png",
      "TokenCost": 1,
      "TokenCostLimited": 1,
      "MinLevelAppears": 1,
      "MaxLevelAppears": 1,
      "SpawnsInSmallCase": false,
      "SpawnsInLargeCase": false,
      "PrimaryGroup": {
        "Category": "Firearm",
        "Rarity": 10.0,
        "RequiredQuest": null,
        "ItemsToSpawn": 1,
        "MinAmmoCapacity": 6,
        "MaxAmmoCapacity": 13,
        "NumMagsSpawned": 3,
        "NumClipsSpawned": 3,
        "NumRoundsSpawned": 8,
        "SpawnMagAndClip": false,
        "BespokeAttachmentChance": 0.5,
        "IsCompatibleMagazine": false,
        "AutoPopulateGroup": false,
        "ForceSpawnAllSubPools": false,
        "IDOverride": [],
        "Eras": [],
        "Sets": [],
        "Sizes": [],
        "Actions": [],
        "Modes": [],
        "ExcludedModes": [],
        "FeedOptions": [],
        "MountsAvailable": [],
        "RoundPowers": [],
        "Features": [],
        "MeleeStyles": [],
        "MeleeHandedness": [],
        "MountTypes": [],
        "PowerupTypes": [],
        "ThrownTypes": [],
        "ThrownDamageTypes": [],
        "SubGroups": [
          {
            "Category": "Firearm",
            "Rarity": 10.0,
            "RequiredQuest": null,
            "ItemsToSpawn": "_10_AmmoShopMultiplier_",
            "MinAmmoCapacity": 6,
            "MaxAmmoCapacity": 13,
            "NumMagsSpawned": 3,
            "NumClipsSpawned": 3,
            "NumRoundsSpawned": 8,
            "SpawnMagAndClip": false,
            "BespokeAttachmentChance": 0.5,
            "IsCompatibleMagazine": false,
            "AutoPopulateGroup": false,
            "ForceSpawnAllSubPools": false,
            "IDOverride": [
              "_AmmoIdTiers0_"
            ],
            "Eras": [],
            "Sets": [],
            "Sizes": [],
            "Actions": [],
            "Modes": [],
            "ExcludedModes": [],
            "FeedOptions": [],
            "MountsAvailable": [],
            "RoundPowers": [],
            "Features": [],
            "MeleeStyles": [],
            "MeleeHandedness": [],
            "MountTypes": [],
            "PowerupTypes": [],
            "ThrownTypes": [],
            "ThrownDamageTypes": [],
            "SubGroups": null
          },
          {
            "Category": "Firearm",
            "Rarity": 10.0,
            "RequiredQuest": null,
            "ItemsToSpawn": "_10_AmmoShopMultiplier_",
            "MinAmmoCapacity": 6,
            "MaxAmmoCapacity": 13,
            "NumMagsSpawned": 3,
            "NumClipsSpawned": 3,
            "NumRoundsSpawned": 8,
            "SpawnMagAndClip": false,
            "BespokeAttachmentChance": 0.5,
            "IsCompatibleMagazine": false,
            "AutoPopulateGroup": false,
            "ForceSpawnAllSubPools": false,
            "IDOverride": [
              "_AmmoIdTiers1_"
            ],
            "Eras": [],
            "Sets": [],
            "Sizes": [],
            "Actions": [],
            "Modes": [],
            "ExcludedModes": [],
            "FeedOptions": [],
            "MountsAvailable": [],
            "RoundPowers": [],
            "Features": [],
            "MeleeStyles": [],
            "MeleeHandedness": [],
            "MountTypes": [],
            "PowerupTypes": [],
            "ThrownTypes": [],
            "ThrownDamageTypes": [],
            "SubGroups": null
          }
        ]
      },
      "BackupGroup": null
    },
    {
      "_Name": "cheap boolets H2",
      "Type": "Firearm",
      "IconName": "bullets.png",
      "TokenCost": 1,
      "TokenCostLimited": 1,
      "MinLevelAppears": 1,
      "MaxLevelAppears": 1,
      "SpawnsInSmallCase": false,
      "SpawnsInLargeCase": false,
      "PrimaryGroup": {
        "Category": "Firearm",
        "Rarity": 10.0,
        "RequiredQuest": null,
        "ItemsToSpawn": 1,
        "MinAmmoCapacity": 6,
        "MaxAmmoCapacity": 13,
        "NumMagsSpawned": 3,
        "NumClipsSpawned": 3,
        "NumRoundsSpawned": 8,
        "SpawnMagAndClip": false,
        "BespokeAttachmentChance": 0.5,
        "IsCompatibleMagazine": false,
        "AutoPopulateGroup": false,
        "ForceSpawnAllSubPools": false,
        "IDOverride": [],
        "Eras": [],
        "Sets": [],
        "Sizes": [],
        "Actions": [],
        "Modes": [],
        "ExcludedModes": [],
        "FeedOptions": [],
        "MountsAvailable": [],
        "RoundPowers": [],
        "Features": [],
        "MeleeStyles": [],
        "MeleeHandedness": [],
        "MountTypes": [],
        "PowerupTypes": [],
        "ThrownTypes": [],
        "ThrownDamageTypes": [],
        "SubGroups": [
          {
            "Category": "Firearm",
            "Rarity": 8.0,
            "RequiredQuest": null,
            "ItemsToSpawn": "_10_AmmoShopMultiplier_",
            "MinAmmoCapacity": 6,
            "MaxAmmoCapacity": 13,
            "NumMagsSpawned": 3,
            "NumClipsSpawned": 3,
            "NumRoundsSpawned": 8,
            "SpawnMagAndClip": false,
            "BespokeAttachmentChance": 0.5,
            "IsCompatibleMagazine": false,
            "AutoPopulateGroup": false,
            "ForceSpawnAllSubPools": false,
            "IDOverride": [
              "_AmmoIdTiers0_"
            ],
            "Eras": [],
            "Sets": [],
            "Sizes": [],
            "Actions": [],
            "Modes": [],
            "ExcludedModes": [],
            "FeedOptions": [],
            "MountsAvailable": [],
            "RoundPowers": [],
            "Features": [],
            "MeleeStyles": [],
            "MeleeHandedness": [],
            "MountTypes": [],
            "PowerupTypes": [],
            "ThrownTypes": [],
            "ThrownDamageTypes": [],
            "SubGroups": null
          },
          {
            "Category": "Firearm",
            "Rarity": 10.0,
            "RequiredQuest": null,
            "ItemsToSpawn": "_10_AmmoShopMultiplier_",
            "MinAmmoCapacity": 6,
            "MaxAmmoCapacity": 13,
            "NumMagsSpawned": 3,
            "NumClipsSpawned": 3,
            "NumRoundsSpawned": 8,
            "SpawnMagAndClip": false,
            "BespokeAttachmentChance": 0.5,
            "IsCompatibleMagazine": false,
            "AutoPopulateGroup": false,
            "ForceSpawnAllSubPools": false,
            "IDOverride": [
              "_AmmoIdTiers1_"
            ],
            "Eras": [],
            "Sets": [],
            "Sizes": [],
            "Actions": [],
            "Modes": [],
            "ExcludedModes": [],
            "FeedOptions": [],
            "MountsAvailable": [],
            "RoundPowers": [],
            "Features": [],
            "MeleeStyles": [],
            "MeleeHandedness": [],
            "MountTypes": [],
            "PowerupTypes": [],
            "ThrownTypes": [],
            "ThrownDamageTypes": [],
            "SubGroups": null
          },
          {
            "Category": "Firearm",
            "Rarity": 7.0,
            "RequiredQuest": null,
            "ItemsToSpawn": "_10_AmmoShopMultiplier_",
            "MinAmmoCapacity": 6,
            "MaxAmmoCapacity": 13,
            "NumMagsSpawned": 3,
            "NumClipsSpawned": 3,
            "NumRoundsSpawned": 8,
            "SpawnMagAndClip": false,
            "BespokeAttachmentChance": 0.5,
            "IsCompatibleMagazine": false,
            "AutoPopulateGroup": false,
            "ForceSpawnAllSubPools": false,
            "IDOverride": [
              "_AmmoIdTiers2_"
            ],
            "Eras": [],
            "Sets": [],
            "Sizes": [],
            "Actions": [],
            "Modes": [],
            "ExcludedModes": [],
            "FeedOptions": [],
            "MountsAvailable": [],
            "RoundPowers": [],
            "Features": [],
            "MeleeStyles": [],
            "MeleeHandedness": [],
            "MountTypes": [],
            "PowerupTypes": [],
            "ThrownTypes": [],
            "ThrownDamageTypes": [],
            "SubGroups": null
          }
        ]
      },
      "BackupGroup": null
    },
    {
      "_Name": "cheap boolets H3",
      "Type": "Firearm",
      "IconName": "bullets.png",
      "TokenCost": 1,
      "TokenCostLimited": 1,
      "MinLevelAppears": 1,
      "MaxLevelAppears": 1,
      "SpawnsInSmallCase": false,
      "SpawnsInLargeCase": false,
      "PrimaryGroup": {
        "Category": "Firearm",
        "Rarity": 10.0,
        "RequiredQuest": null,
        "ItemsToSpawn": 1,
        "MinAmmoCapacity": 6,
        "MaxAmmoCapacity": 13,
        "NumMagsSpawned": 3,
        "NumClipsSpawned": 3,
        "NumRoundsSpawned": 8,
        "SpawnMagAndClip": false,
        "BespokeAttachmentChance": 0.5,
        "IsCompatibleMagazine": false,
        "AutoPopulateGroup": false,
        "ForceSpawnAllSubPools": false,
        "IDOverride": [],
        "Eras": [],
        "Sets": [],
        "Sizes": [],
        "Actions": [],
        "Modes": [],
        "ExcludedModes": [],
        "FeedOptions": [],
        "MountsAvailable": [],
        "RoundPowers": [],
        "Features": [],
        "MeleeStyles": [],
        "MeleeHandedness": [],
        "MountTypes": [],
        "PowerupTypes": [],
        "ThrownTypes": [],
        "ThrownDamageTypes": [],
        "SubGroups": [
          {
            "Category": "Firearm",
            "Rarity": 10.0,
            "RequiredQuest": null,
            "ItemsToSpawn": "_10_AmmoShopMultiplier_",
            "MinAmmoCapacity": 6,
            "MaxAmmoCapacity": 13,
            "NumMagsSpawned": 3,
            "NumClipsSpawned": 3,
            "NumRoundsSpawned": 8,
            "SpawnMagAndClip": false,
            "BespokeAttachmentChance": 0.5,
            "IsCompatibleMagazine": false,
            "AutoPopulateGroup": false,
            "ForceSpawnAllSubPools": false,
            "IDOverride": [
              "_AmmoIdTiers0_"
            ],
            "Eras": [],
            "Sets": [],
            "Sizes": [],
            "Actions": [],
            "Modes": [],
            "ExcludedModes": [],
            "FeedOptions": [],
            "MountsAvailable": [],
            "RoundPowers": [],
            "Features": [],
            "MeleeStyles": [],
            "MeleeHandedness": [],
            "MountTypes": [],
            "PowerupTypes": [],
            "ThrownTypes": [],
            "ThrownDamageTypes": [],
            "SubGroups": null
          },
          {
            "Category": "Firearm",
            "Rarity": 8.0,
            "RequiredQuest": null,
            "ItemsToSpawn": "_10_AmmoShopMultiplier_",
            "MinAmmoCapacity": 6,
            "MaxAmmoCapacity": 13,
            "NumMagsSpawned": 3,
            "NumClipsSpawned": 3,
            "NumRoundsSpawned": 8,
            "SpawnMagAndClip": false,
            "BespokeAttachmentChance": 0.5,
            "IsCompatibleMagazine": false,
            "AutoPopulateGroup": false,
            "ForceSpawnAllSubPools": false,
            "IDOverride": [
              "_AmmoIdTiers1_"
            ],
            "Eras": [],
            "Sets": [],
            "Sizes": [],
            "Actions": [],
            "Modes": [],
            "ExcludedModes": [],
            "FeedOptions": [],
            "MountsAvailable": [],
            "RoundPowers": [],
            "Features": [],
            "MeleeStyles": [],
            "MeleeHandedness": [],
            "MountTypes": [],
            "PowerupTypes": [],
            "ThrownTypes": [],
            "ThrownDamageTypes": [],
            "SubGroups": null
          },
          {
            "Category": "Firearm",
            "Rarity": 9.0,
            "RequiredQuest": null,
            "ItemsToSpawn": "_10_AmmoShopMultiplier_",
            "MinAmmoCapacity": 6,
            "MaxAmmoCapacity": 13,
            "NumMagsSpawned": 3,
            "NumClipsSpawned": 3,
            "NumRoundsSpawned": 8,
            "SpawnMagAndClip": false,
            "BespokeAttachmentChance": 0.5,
            "IsCompatibleMagazine": false,
            "AutoPopulateGroup": false,
            "ForceSpawnAllSubPools": false,
            "IDOverride": [
              "_AmmoIdTiers2_"
            ],
            "Eras": [],
            "Sets": [],
            "Sizes": [],
            "Actions": [],
            "Modes": [],
            "ExcludedModes": [],
            "FeedOptions": [],
            "MountsAvailable": [],
            "RoundPowers": [],
            "Features": [],
            "MeleeStyles": [],
            "MeleeHandedness": [],
            "MountTypes": [],
            "PowerupTypes": [],
            "ThrownTypes": [],
            "ThrownDamageTypes": [],
            "SubGroups": null
          },
          {
            "Category": "Firearm",
            "Rarity": 7.0,
            "RequiredQuest": null,
            "ItemsToSpawn": "_10_AmmoShopMultiplier_",
            "MinAmmoCapacity": 6,
            "MaxAmmoCapacity": 13,
            "NumMagsSpawned": 3,
            "NumClipsSpawned": 3,
            "NumRoundsSpawned": 8,
            "SpawnMagAndClip": false,
            "BespokeAttachmentChance": 0.5,
            "IsCompatibleMagazine": false,
            "AutoPopulateGroup": false,
            "ForceSpawnAllSubPools": false,
            "IDOverride": [
              "_AmmoIdTiers3_"
            ],
            "Eras": [],
            "Sets": [],
            "Sizes": [],
            "Actions": [],
            "Modes": [],
            "ExcludedModes": [],
            "FeedOptions": [],
            "MountsAvailable": [],
            "RoundPowers": [],
            "Features": [],
            "MeleeStyles": [],
            "MeleeHandedness": [],
            "MountTypes": [],
            "PowerupTypes": [],
            "ThrownTypes": [],
            "ThrownDamageTypes": [],
            "SubGroups": null
          }
        ]
      },
      "BackupGroup": null
    },

    {
      "_Name": "premium boolets H0",
      "Type": "Equipment",
      "IconName": "betterBullets.png",
      "TokenCost": 2,
      "TokenCostLimited": 2,
      "MinLevelAppears": 0,
      "MaxLevelAppears": 0,
      "SpawnsInSmallCase": false,
      "SpawnsInLargeCase": false,
      "PrimaryGroup": {
        "Category": "Cartridge",
        "Rarity": 10.0,
        "RequiredQuest": null,
        "ItemsToSpawn": "_15_AmmoShopMultiplier_",
        "MinAmmoCapacity": 6,
        "MaxAmmoCapacity": 13,
        "NumMagsSpawned": 3,
        "NumClipsSpawned": 3,
        "NumRoundsSpawned": 8,
        "SpawnMagAndClip": false,
        "BespokeAttachmentChance": 0.5,
        "IsCompatibleMagazine": false,
        "AutoPopulateGroup": false,
        "ForceSpawnAllSubPools": false,
        "IDOverride": [],
        "Eras": [],
        "Sets": [],
        "Sizes": [],
        "Actions": [],
        "Modes": [],
        "ExcludedModes": [],
        "FeedOptions": [],
        "MountsAvailable": [],
        "RoundPowers": [],
        "Features": [],
        "MeleeStyles": [],
        "MeleeHandedness": [],
        "MountTypes": [],
        "PowerupTypes": [],
        "ThrownTypes": [],
        "ThrownDamageTypes": [],
        "SubGroups": [
          {
            "Category": "Firearm",
            "Rarity": 10.0,
            "RequiredQuest": null,
            "ItemsToSpawn": "_15_AmmoShopMultiplier_",
            "MinAmmoCapacity": 6,
            "MaxAmmoCapacity": 13,
            "NumMagsSpawned": 3,
            "NumClipsSpawned": 3,
            "NumRoundsSpawned": 8,
            "SpawnMagAndClip": false,
            "BespokeAttachmentChance": 0.5,
            "IsCompatibleMagazine": false,
            "AutoPopulateGroup": false,
            "ForceSpawnAllSubPools": false,
            "IDOverride": [
              "_AmmoIdTiers0_"
            ],
            "Eras": [],
            "Sets": [],
            "Sizes": [],
            "Actions": [],
            "Modes": [],
            "ExcludedModes": [],
            "FeedOptions": [],
            "MountsAvailable": [],
            "RoundPowers": [],
            "Features": [],
            "MeleeStyles": [],
            "MeleeHandedness": [],
            "MountTypes": [],
            "PowerupTypes": [],
            "ThrownTypes": [],
            "ThrownDamageTypes": [],
            "SubGroups": null
          },
          {
            "Category": "Firearm",
            "Rarity": 20.0,
            "RequiredQuest": null,
            "ItemsToSpawn": "_15_AmmoShopMultiplier_",
            "MinAmmoCapacity": 6,
            "MaxAmmoCapacity": 13,
            "NumMagsSpawned": 3,
            "NumClipsSpawned": 3,
            "NumRoundsSpawned": 8,
            "SpawnMagAndClip": false,
            "BespokeAttachmentChance": 0.5,
            "IsCompatibleMagazine": false,
            "AutoPopulateGroup": false,
            "ForceSpawnAllSubPools": false,
            "IDOverride": [
              "_AmmoIdTiers1_"
            ],
            "Eras": [],
            "Sets": [],
            "Sizes": [],
            "Actions": [],
            "Modes": [],
            "ExcludedModes": [],
            "FeedOptions": [],
            "MountsAvailable": [],
            "RoundPowers": [],
            "Features": [],
            "MeleeStyles": [],
            "MeleeHandedness": [],
            "MountTypes": [],
            "PowerupTypes": [],
            "ThrownTypes": [],
            "ThrownDamageTypes": [],
            "SubGroups": null
          }
        ]
      },
      "BackupGroup": null
    },
    {
      "_Name": "mag",
      "Type": "Equipment",
      "IconName": "magazine.png",
      "TokenCost": "_MagCost_",
      "TokenCostLimited": "_MagCost_",
      "MinLevelAppears": 0,
      "MaxLevelAppears": 0,
      "SpawnsInSmallCase": true,
      "SpawnsInLargeCase": false,
      "PrimaryGroup": {
        "Category": "Firearm",
        "Rarity": 10.0,
        "RequiredQuest": null,
        "ItemsToSpawn": 1,
        "MinAmmoCapacity": 6,
        "MaxAmmoCapacity": 13,
        "NumMagsSpawned": 3,
        "NumClipsSpawned": 3,
        "NumRoundsSpawned": 8,
        "SpawnMagAndClip": false,
        "BespokeAttachmentChance": 0.5,
        "IsCompatibleMagazine": false,
        "AutoPopulateGroup": false,
        "ForceSpawnAllSubPools": false,
        "IDOverride": "_MagazineIds_",
        "Eras": [],
        "Sets": [],
        "Sizes": [],
        "Actions": [],
        "Modes": [],
        "ExcludedModes": [],
        "FeedOptions": [],
        "MountsAvailable": [],
        "RoundPowers": [],
        "Features": [],
        "MeleeStyles": [],
        "MeleeHandedness": [],
        "MountTypes": [],
        "PowerupTypes": [],
        "ThrownTypes": [],
        "ThrownDamageTypes": [],
        "SubGroups": null
      },
      "BackupGroup": null
    },

    {
      "_Name": "Frags",
      "Type": "Consumable",
      "IconName": "TNH_Icon_grenade",
      "TokenCost": 3,
      "TokenCostLimited": 1,
      "MinLevelAppears": 0,
      "MaxLevelAppears": 5,
      "SpawnsInSmallCase": false,
      "SpawnsInLargeCase": false,
      "PrimaryGroup":
      {
      "Category": "Thrown",
      "Rarity": 4.0,
      "RequiredQuest": null,
      "ItemsToSpawn": 1,
      "MinAmmoCapacity": -1,
      "MaxAmmoCapacity": -1,
      "NumMagsSpawned": 3,
      "NumClipsSpawned": 3,
      "NumRoundsSpawned": 8,
      "SpawnMagAndClip": false,
      "BespokeAttachmentChance": 0.5,
      "IsCompatibleMagazine": false,
      "AutoPopulateGroup": false,
      "ForceSpawnAllSubPools": false,
      "IDOverride": [
        "Stielhandgranate",
        "CyberGrenade",
        "No69Grenade",
        "PinnedGrenadeF1M1916",
        "PinnedGrenadeF1Russia",
        "PinnedGrenadeFMK2",
        "PinnedGrenadeHE36MillsBomb",
        "PinnedGrenadeM219",
        "PinnedGrenadeM26",
        "PinnedGrenadeM340",
        "PinnedGrenadeM67",
        "PinnedGrenadeMk2",
        "PinnedGrenadeRG42",
        "PinnedGrenadeRG5",
        "PinnedGrenadeRGN",
        "PinnedGrenadeRGO",
        "PinnedGrenadeT13Beano",
        "PinnedGrenadeURG86"
      ],
      "Eras": [],
      "Sets": [],
      "Sizes": [],
      "Actions": [],
      "Modes": [],
      "ExcludedModes": [],
      "FeedOptions": [],
      "MountsAvailable": [],
      "RoundPowers": [],
      "Features": [],
      "MeleeStyles": [],
      "MeleeHandedness": [],
      "MountTypes": [],
      "PowerupTypes": [],
      "ThrownTypes": [],
      "ThrownDamageTypes": [],
      "SubGroups": null
    },
      "BackupGroup": null
    },
    {
      "_Name": "Flashbangs",
      "Type": "Consumable",
      "IconName": "TNH_Icon_utility_grenade",
      "TokenCost": 1,
      "TokenCostLimited": 6,
      "MinLevelAppears": 0,
      "MaxLevelAppears": 5,
      "SpawnsInSmallCase": false,
      "SpawnsInLargeCase": false,
      "PrimaryGroup":
      {
        "Category": "Thrown",
        "Rarity": 3.0,
        "RequiredQuest": null,
        "ItemsToSpawn": 4,
        "MinAmmoCapacity": -1,
        "MaxAmmoCapacity": -1,
        "NumMagsSpawned": 3,
        "NumClipsSpawned": 3,
        "NumRoundsSpawned": 8,
        "SpawnMagAndClip": false,
        "BespokeAttachmentChance": 0.5,
        "IsCompatibleMagazine": false,
        "AutoPopulateGroup": false,
        "ForceSpawnAllSubPools": false,
        "IDOverride": [
          "PinnedGrenadeXM84"
        ],
        "Eras": [],
        "Sets": [],
        "Sizes": [],
        "Actions": [],
        "Modes": [],
        "ExcludedModes": [],
        "FeedOptions": [],
        "MountsAvailable": [],
        "RoundPowers": [],
        "Features": [],
        "MeleeStyles": [],
        "MeleeHandedness": [],
        "MountTypes": [],
        "PowerupTypes": [],
        "ThrownTypes": [],
        "ThrownDamageTypes": [],
        "SubGroups": null
      },
      "BackupGroup": null
    }
    
  ],
  "Levels": [
    {
      "_Name": "H1",
      "NumOverrideTokensForHold": 2,
      "MinSupplyPoints": 2,
      "MaxSupplyPoints": 2,
      "MinConstructors": 1,
      "MaxConstructors": 1,
      "MinPanels": 0,
      "MaxPanels": 0,
      "MinBoxesSpawned": 2,
      "MaxBoxesSpawned": 2,
      "MinTokensPerSupply": 1,
      "MaxTokensPerSupply": 1,
      "BoxTokenChance": 1.0,
      "BoxHealthChance": 1.0,
      "PossiblePanelTypes": [],
      "TakeChallenge": {
        "TurretType": "Machinegun",
        "EnemyType": "sosig_Replicant_Light-_NameId_",
        "NumTurrets": 1,
        "NumGuards": 1,
        "IFFUsed": 1
      },
      "HoldPhases": [
        {
          "Encryptions": [
            "Static"
          ],
          "MinTargets": "_10_EncryptionsModifier_",
          "MaxTargets": "_10_EncryptionsModifier_",
          "MinTargetsLimited": "_10_EncryptionsModifier_",
          "MaxTargetsLimited": "_10_EncryptionsModifier_",
          "EnemyType": [
            "sosig_Robro_HoldSpecific-_NameId_"
          ],
          "LeaderType": "sosig_Robro_HoldSpecific-_NameId_",
          "MinEnemies": 1,
          "MaxEnemies": 1,
          "MaxEnemiesAlive": 1,
          "MaxDirections": 1,
          "SpawnCadence": 45.0,
          "ScanTime": 10.0,
          "WarmupTime": 5.0,
          "IFFUsed": 1,
          "GrenadeChance": 0.0,
          "GrenadeType": "Sosiggrenade_Flash",
          "SwarmPlayer": true
        },
        {
          "Encryptions": [
            "Stealth"
          ],
          "MinTargets": "_10_EncryptionsModifier_",
          "MaxTargets": "_10_EncryptionsModifier_",
          "MinTargetsLimited": "_10_EncryptionsModifier_",
          "MaxTargetsLimited": "_10_EncryptionsModifier_",
          "EnemyType": [
            "sosig_Robro_HoldSpecific-_NameId_"
          ],
          "LeaderType": "sosig_Robro_HoldSpecific-_NameId_",
          "MinEnemies": 1,
          "MaxEnemies": 1,
          "MaxEnemiesAlive": 1,
          "MaxDirections": 1,
          "SpawnCadence": 30.0,
          "ScanTime": 10.0,
          "WarmupTime": 1.0,
          "IFFUsed": 1,
          "GrenadeChance": 0.0,
          "GrenadeType": "Sosiggrenade_Flash",
          "SwarmPlayer": true
        }
      ],
      "SupplyChallenge": {
        "TurretType": "Machinegun",
        "EnemyType": "sosig_Replicant_Light-_NameId_",
        "NumTurrets": 1,
        "NumGuards": 0,
        "IFFUsed": 1
      },
      "Patrols": [
        {
          "EnemyType": [
            "sosig_Replicant_Light-_NameId_"
          ],
          "LeaderType": "sosig_Replicant_Light-_NameId_",
          "PatrolSize": 2,
          "MaxPatrols": 5,
          "MaxPatrolsLimited": 3,
          "PatrolCadence": 20.0,
          "PatrolCadenceLimited": 40.0,
          "IFFUsed": 1,
          "SwarmPlayer": false,
          "AssualtSpeed": "Walking",
          "IsBoss": false,
          "DropChance": 1,
          "DropsHealth": true
        }
      ]
    }
  ],
  "LevelsEndless": [
    {
      "NumOverrideTokensForHold": 4,
      "MinSupplyPoints": 2,
      "MaxSupplyPoints": 2,
      "MinConstructors": 1,
      "MaxConstructors": 1,
      "MinPanels": 1,
      "MaxPanels": 1,
      "MinBoxesSpawned": 1,
      "MaxBoxesSpawned": 1,
      "MinTokensPerSupply": 0,
      "MaxTokensPerSupply": 0,
      "BoxTokenChance": 0.0,
      "BoxHealthChance": 1,
      "PossiblePanelTypes": [
        "MagDuplicator"
      ],
      "TakeChallenge": {
        "TurretType": "SMG",
        "EnemyType": "M_Swat_Riflewiener",
        "NumTurrets": 2,
        "NumGuards": 0,
        "IFFUsed": 1
      },
      "HoldPhases": [
        {
          "Encryptions": [
            "Static",
            "Swarm",
            
            "Stealth",
            "Agile",
            
            "Hardened",
            "Recursive",
            
            "Regenerative"
          ],
          "MinTargets": "_10_EncryptionsModifier_",
          "MaxTargets": "_10_EncryptionsModifier_",
          "MinTargetsLimited": "_10_EncryptionsModifier_",
          "MaxTargetsLimited": "_10_EncryptionsModifier_",
          "EnemyType": [
            "sosig_Robro_HoldSpecific-_NameId_"
          ],
          "LeaderType": "sosig_Robro_HoldSpecific-_NameId_",
          "MinEnemies": 1,
          "MaxEnemies": 1,
          "MaxEnemiesAlive": 1,
          "MaxDirections": 2,
          "SpawnCadence": 90.0,
          "ScanTime": 10.0,
          "WarmupTime": 5.0,
          "IFFUsed": 1,
          "GrenadeChance": 0.0,
          "GrenadeType": "Sosiggrenade_Flash",
          "SwarmPlayer": true
        }
      ],
      "SupplyChallenge": {
        "TurretType": "SMG",
        "EnemyType": "M_Swat_Riflewiener",
        "NumTurrets": 1,
        "NumGuards": 0,
        "IFFUsed": 1
      },
      "Patrols": [
        {
          "EnemyType": [
            "sosig_Replicant_Light-_NameId_"
          ],
          "LeaderType": "sosig_Replicant_Light-_NameId_",
          "PatrolSize": 1,
          "MaxPatrols": 6,
          "MaxPatrolsLimited": 4,
          "PatrolCadence": 60.0,
          "PatrolCadenceLimited": 100.0,
          "IFFUsed": 1,
          "SwarmPlayer": false,
          "AssualtSpeed": "Walking",
          "IsBoss": false,
          "DropChance": 1,
          "DropsHealth": true
        }
      ]
    }
  ]
}
